{
    "@type": "type.googleapis.com/swiggy.presentation.food.v2.Restaurant",
    "info": {
        "id": "151518",
        "name": "Bakery World",
        "cloudinaryImageId": "mt2aggiscfl3yviatwng",
        "locality": "Parasia Road",
        "areaName": "Parasia Road",
        "costForTwo": "₹250 for two",
        "cuisines": [
            "Bakery",
            "Ice Cream",
            "Snacks",
            "Beverages"
        ],
        "avgRating": 4.3,
        "veg": true,
        "parentId": "40363",
        "avgRatingString": "4.3",
        "totalRatingsString": "261",
        "sla": {
            "deliveryTime": 48,
            "lastMileTravel": 14.1,
            "serviceability": "SERVICEABLE",
            "slaString": "45-50 mins",
            "lastMileTravelString": "14.1 km",
            "iconType": "ICON_TYPE_EMPTY"
        },
        "availability": {
            "nextCloseTime": "2025-04-27 22:30:00",
            "opened": true
        },
        "badges": {
            "imageBadges": [
                {
                    "imageId": "v1695133679/badges/Pure_Veg111.png",
                    "description": "pureveg"
                }
            ]
        },
        "isOpen": true,
        "aggregatedDiscountInfoV2": {},
        "type": "F",
        "badgesV2": {
            "entityBadges": {
                "imageBased": {
                    "badgeObject": [
                        {
                            "attributes": {
                                "description": "pureveg",
                                "imageId": "v1695133679/badges/Pure_Veg111.png"
                            }
                        }
                    ]
                },
                "textBased": {},
                "textExtendedBadges": {}
            }
        },
        "orderabilityCommunication": {
            "title": {},
            "subTitle": {},
            "message": {},
            "customIcon": {}
        },
        "differentiatedUi": {
            "displayType": "ADS_UI_DISPLAY_TYPE_ENUM_DEFAULT",
            "differentiatedUiMediaDetails": {
                "mediaType": "ADS_MEDIA_ENUM_IMAGE",
                "lottie": {},
                "video": {}
            }
        },
        "reviewsSummary": {},
        "displayType": "RESTAURANT_DISPLAY_TYPE_DEFAULT",
        "restaurantOfferPresentationInfo": {},
        "externalRatings": {
            "aggregatedRating": {
                "rating": "--"
            }
        },
        "ratingsDisplayPreference": "RATINGS_DISPLAY_PREFERENCE_SHOW_SWIGGY"
    },
    "analytics": {
        "context": "seo-data-b571b79c-bb4b-4a65-91d1-63815ad95dbe"
    },
    "cta": {
        "link": "https://www.swiggy.com/city/chhindwara/bakery-world-parasia-road-rest151518",
        "text": "RESTAURANT_MENU",
        "type": "WEBLINK"
    },
    "widgetId": "collectionV5RestaurantListWidget_SimRestoRelevance_food_seo"
}